dataDisk/__init__.py
dataDisk/data_sources.py
dataDisk/parallel_processor.py
dataDisk/pipeline.py
dataDisk/transformation.py
dataDisk/validator.py
datadisk-1.2.0.dist-info/METADATA
datadisk-1.2.0.dist-info/WHEEL
datadisk-1.2.0.dist-info/RECORD
